uiipythonapi/__init__.py
uiipythonapi/client.py
uiipythonapi-1.0.1.dist-info/METADATA
uiipythonapi-1.0.1.dist-info/WHEEL
uiipythonapi-1.0.1.dist-info/top_level.txt
uiipythonapi-1.0.1.dist-info/RECORD
