Metadata-Version: 2.1
Name: uiipythonapi
Version: 1.0.1
Summary: A client implementation for Virtomize Unattended Install Images API
Home-page: https://github.com/virtomize/uii-python-api
Author: Virtomize GmbH
Author-email: api@virtomize.com
License: BSD 2-clause
Classifier: Intended Audience :: Science/Research
Classifier: Programming Language :: Python :: 3
Classifier: Programming Language :: Python :: 3.4
Classifier: Programming Language :: Python :: 3.8
Requires-Dist: requests
